{"@context":"http://iiif.io/api/presentation/2/context.json","@id":"https://architecturasinica.org/apps/tcadrt-data/data/manifests/manifests/m51151480841.json","@type":"sc:Manifest","label":"Bao'ensi, Nanjing","attribution":"Architectura Sinica, work in the Public Domain","logo":"https://iiif.library.vanderbilt.edu/iiif/2/vu_gallery_logo1.png/full/!100,100/0/default.jpg","metadata":[{"label":"Title","value":"Bao'ensi, Nanjing"},{"label":"Description","value":"Wall of Buddhas inside the Porcelain Pagoda, 2015, Great Bao’en Monastery 大報恩寺琉璃塔佛像墻 (Photo: added by Y Zou, 2021)"},{"label":"Tags","value":["baoensi","nanjing","baoen","monastery","報恩寺"]}],"sequences":[{"@id":"https://architecturasinica.org/apps/tcadrt-data/data/manifests/manifests/m51151480841/seq/1","@type":"sc:Sequence","label":{"@value":"Normal Sequence","@language":"en"},"canvases":[{"@id":"https://architecturasinica.org/apps/tcadrt-data/data/manifests/manifests/m51151480841/canvas/1","@type":"sc:Canvas","label":"Full View","width":4000,"height":3000,"images":[{"@context":"http://iiif.io/api/presentation/2/context.json","@id":"https://architecturasinica.org/apps/tcadrt-data/data/manifests/manifests/m51151480841/image/1","@type":"oa:Annotation","motivation":"sc:painting","resource":{"@id":"https://iiif.library.vanderbilt.edu/iiif/2/attcat%2F51151480841.jpg/full/full/0/default.jpg","@type":"dctypes:Image","format":"image/jpg","width":4000,"height":3000,"service":{"@context":"http://iiif.io/api/presentation/2/context.json","@id":"https://iiif.library.vanderbilt.edu/iiif/2/attcat%2F51151480841.jpg","profile":["http://iiif.io/api/image/2/level1.json",{"formats":["jpg"],"qualities":["native","color","gray"],"supports":["regionByPct","regionSquare","sizeByForcedWh","sizeByWh","sizeAboveFull","rotationBy90s","mirroring"]}]}},"on":"https://architecturasinica.org/apps/tcadrt-data/data/manifests/manifests/m51151480841/canvas/1"}]}]}],"structures":[],"viewingDirection":"left-to-right","viewingHint":"individuals"}